zerocache/__init__.py
zerocache/client.py
zerocache/decorators.py
zerocache/listener.py
zerocache/server.py
zerocache-0.0.2.dist-info/LICENSE.txt
zerocache-0.0.2.dist-info/METADATA
zerocache-0.0.2.dist-info/WHEEL
zerocache-0.0.2.dist-info/top_level.txt
zerocache-0.0.2.dist-info/RECORD
