Metadata-Version: 2.1
Name: zerocache
Version: 0.0.2
Summary: A dead-simple, zeroconf-based expansion of 'cachetools' TLRUCache, with multi-region redundancy
Author-email: Victor Yap <starlocke@gmail.com>
Project-URL: Homepage, https://github.com/starlocke/zerocache
Project-URL: Issues, https://github.com/starlocke/zerocache/issues
Classifier: Programming Language :: Python :: 3
Classifier: License :: OSI Approved :: GNU General Public License v3 (GPLv3)
Requires-Python: >=3.11
License-File: LICENSE.txt
Requires-Dist: requests
Requires-Dist: bottle
Requires-Dist: zeroconf
Requires-Dist: cachetools
Requires-Dist: paste
